Metadata-Version: 2.1
Name: bio-embeddings-tape-proteins
Version: 0.5
Summary: Repostory of Protein Benchmarking and Modeling
Home-page: https://github.com/songlab-cal/tape
Author: Roshan Rao, Nick Bhattacharya, Neil Thomas
Author-email: roshan_rao@berkeley.edu, nickbhat@berkeley.edu, nthomas@berkeley.edu
License: BSD 3-Clause License        
Keywords: Proteins,Deep Learning,Pytorch,TAPE
Platform: UNKNOWN
Classifier: Programming Language :: Python :: 3.6
Classifier: Programming Language :: Python :: 3.7
Classifier: Programming Language :: Python :: 3.8
Classifier: Operating System :: POSIX :: Linux
Classifier: Intended Audience :: Developers
Classifier: Intended Audience :: Science/Research
Classifier: Topic :: Scientific/Engineering :: Artificial Intelligence
Classifier: Topic :: Scientific/Engineering :: Bio-Informatics
License-File: LICENSE
Requires-Dist: torch (<1.10,>=1.0)
Requires-Dist: tqdm
Requires-Dist: tensorboardX
Requires-Dist: scipy
Requires-Dist: lmdb
Requires-Dist: boto3
Requires-Dist: requests
Requires-Dist: biopython
Requires-Dist: filelock
